tsing_spider/__init__.py
tsing_spider/config.py
tsing_spider/finance/__init__.py
tsing_spider/finance/caixin_news.py
tsing_spider/other/__init__.py
tsing_spider/other/dnc_leakmail.py
tsing_spider/porn/__init__.py
tsing_spider/porn/caoliu.py
tsing_spider/porn/everia_club.py
tsing_spider/porn/jav.py
tsing_spider/porn/sex8cc.py
tsing_spider/porn/xarthunter.py
tsing_spider/porn/xhamster.py
tsing_spider/porn/xvideos.py
tsing_spider/social_network/__init__.py
tsing_spider/social_network/douban.py
tsing_spider/test/__init__.py
tsing_spider/test/test_porn.py
tsing_spider/util/__init__.py
tsing_spider/util/hls.py
tsing_spider/util/pyurllib.py
tsing_spider/util/tools.py
tsingspider-1.5.0.dist-info/licenses/LICENSE
tsingspider-1.5.0.dist-info/METADATA
tsingspider-1.5.0.dist-info/WHEEL
tsingspider-1.5.0.dist-info/top_level.txt
tsingspider-1.5.0.dist-info/RECORD
