Metadata-Version: 2.4
Name: tsingspider
Version: 1.5.0
Summary: A spider library of several data sources
Project-URL: github, https://github.com/TsingJyujing/DataSpider
Requires-Python: >=3.9
License-File: LICENSE
Requires-Dist: beautifulsoup4>=4.13.4
Requires-Dist: bencodepy>=0.9.5
Requires-Dist: lxml>=6.0.0
Requires-Dist: m3u8>=6.0.0
Requires-Dist: pycryptodomex>=3.23.0
Requires-Dist: pytest>=8.4.1
Requires-Dist: pytz>=2025.2
Requires-Dist: requests>=2.32.4
Dynamic: license-file
